slothpaste/__init__.py
slothpaste/__main__.py
slothpaste/langs.txt
sloth_paste-1.0.2.dist-info/LICENSE
sloth_paste-1.0.2.dist-info/METADATA
sloth_paste-1.0.2.dist-info/WHEEL
sloth_paste-1.0.2.dist-info/entry_points.txt
sloth_paste-1.0.2.dist-info/top_level.txt
sloth_paste-1.0.2.dist-info/RECORD
