Metadata-Version: 2.1
Name: sloth-paste
Version: 1.0.2
Summary: A simple file content sharing app.
Home-page: https://github.com/bufgix/slothpaste
Author: Bufgix
Author-email: ooruc471@yandex.com
License: MIT
Platform: UNKNOWN
Classifier: License :: OSI Approved :: MIT License
Classifier: Programming Language :: Python :: 3
Classifier: Programming Language :: Python :: 3.7
Requires-Dist: requests
Requires-Dist: beautifulsoup4
Requires-Dist: pygments
Requires-Dist: colorama
Requires-Dist: pyperclip
